Metadata-Version: 2.1
Name: ToushinReader
Version: 0.2.3
Summary: Japanese Mutual Fund data download library.
Home-page: https://github.com/sawadyrr5/ToushinReader
Author: sawady
Author-email: riskreturn5@gmail.com
License: Apache 2.0
Platform: UNKNOWN
Classifier: Programming Language :: Python :: 3
Classifier: Programming Language :: Python :: 3.8
License-File: LICENSE
